fastapi_jwks/__init__.py
fastapi_jwks/dependencies/__init__.py
fastapi_jwks/dependencies/jwk_auth.py
fastapi_jwks/injector/__init__.py
fastapi_jwks/injector/payload_injector.py
fastapi_jwks/models/__init__.py
fastapi_jwks/models/types.py
fastapi_jwks/validators/__init__.py
fastapi_jwks/validators/jwks_validator.py
fastapi_jwks-2.0.1.dist-info/LICENSE
fastapi_jwks-2.0.1.dist-info/METADATA
fastapi_jwks-2.0.1.dist-info/WHEEL
fastapi_jwks-2.0.1.dist-info/RECORD
