Metadata-Version: 2.1
Name: fastapi-jwks
Version: 2.0.1
Summary: A library designed to facilitate the integration of JSON Web Key Set (JWKS) with FastAPI applications
License: MIT
Author: bakdata
Requires-Python: >=3.12
Classifier: License :: OSI Approved :: MIT License
Classifier: Programming Language :: Python :: 3
Classifier: Programming Language :: Python :: 3.12
Requires-Dist: cachetools (>=5.3.3)
Requires-Dist: cryptography (>=44.0.2)
Requires-Dist: fastapi (>=0.111.0,<1.0)
Requires-Dist: httpx (>=0.27.0,<1.0)
Requires-Dist: pydantic (>=2.7.1)
Requires-Dist: pyjwt[crypto] (>=2.8.0)
Requires-Dist: types-cachetools (>=5.3.0.7)
